API/__init__.py
API/modules/__init__.py
API/modules/baseApi.py
API/modules/delete.py
API/modules/get.py
API/modules/patch.py
API/modules/post.py
API/modules/put.py
API/modules/json/__init__.py
API/modules/json/pyJson.py
API/modules/mocker/__init__.py
API/modules/mocker/mocker.py
API/modules/mocker/mocker_internal.py
API/modules/redis_py/__init__.py
API/modules/redis_py/redis.py
API/unittest/__init__.py
API/unittest/test_unittest.py
api_nichotined-1.1.1.dist-info/LICENSE
api_nichotined-1.1.1.dist-info/METADATA
api_nichotined-1.1.1.dist-info/WHEEL
api_nichotined-1.1.1.dist-info/top_level.txt
api_nichotined-1.1.1.dist-info/RECORD
