Metadata-Version: 2.1
Name: api-nichotined
Version: 1.1.1
Summary: API package for testing purpose
Home-page: https://github.com/nichotined/api
Author: Nicholas Frederick
Author-email: nicholas.frederich.lagaunne@gmail.com
License: UNKNOWN
Platform: UNKNOWN
Classifier: Programming Language :: Python :: 3
Classifier: License :: OSI Approved :: MIT License
Classifier: Operating System :: OS Independent
Requires-Dist: requests
Requires-Dist: pytest
Requires-Dist: redis
Requires-Dist: curlify
Requires-Dist: mitmproxy
